resoto_plugin_cleanup_untagged/__init__.py
resoto_plugin_cleanup_untagged/config.py
resoto_plugin_cleanup_untagged-3.7.0.dist-info/METADATA
resoto_plugin_cleanup_untagged-3.7.0.dist-info/WHEEL
resoto_plugin_cleanup_untagged-3.7.0.dist-info/entry_points.txt
resoto_plugin_cleanup_untagged-3.7.0.dist-info/top_level.txt
resoto_plugin_cleanup_untagged-3.7.0.dist-info/RECORD
