Metadata-Version: 2.1
Name: resoto-plugin-cleanup-untagged
Version: 3.7.0
Summary: Resoto Cleanup Untagged Plugin
Author: Some Engineering Inc.
Project-URL: Documentation, https://resoto.com
Project-URL: Source, https://github.com/someengineering/resoto/tree/main/plugins/cleanup_untagged
Classifier: Development Status :: 4 - Beta
Classifier: Intended Audience :: System Administrators
Classifier: Intended Audience :: Information Technology
Classifier: License :: OSI Approved :: Apache Software License
Classifier: Programming Language :: Python :: 3.9
Classifier: Operating System :: POSIX :: Linux
Classifier: Operating System :: Unix
Classifier: Environment :: Console
Classifier: Natural Language :: English
Classifier: Topic :: Security
Classifier: Topic :: Utilities
Requires-Python: >=3.9
Requires-Dist: resotolib ==3.7.0
